{"type":"Topology","objects":{"counties":{"type":"GeometryCollection","geometries":[{"type":"Polygon","id":"01123","properties":{"stateFIPS":"01","state":"Alabama","countyFIPS":"123","name":"Tallapoosa","statePostal":"AL"},"arcs":[[0,1,2,3,4,5,6]]},{"type":"Polygon","id":"01111","properties":{"stateFIPS":"01","state":"Alabama","countyFIPS":"111","name":"Randolph","statePostal":"AL"},"arcs":[[7,8,9,-2,10]]},{"type":"Polygon","id":"01131","properties":{"stateFIPS":"01","state":"Alabama","countyFIPS":"131","name":"Wilcox","statePostal":"AL"},"arcs":[[11,12,13,14,15,16]]},{"type":"Polygon","id":"01001","properties":{"stateFIPS":"01","state":"Alabama","countyFIPS":"001","name":"Autauga","statePostal":"AL"},"arcs":[[17,18,19,20,21]]},{"type":"Polygon","id":"01037","properties":{"stateFIPS":"01","state":"Alabama","countyFIPS":"037","name":"Coosa","statePostal":"AL"},"arcs":[[22,23,24,-7,25,26]]},{"type":"Polygon","id":"01033","properties":{"stateFIPS":"01","state":"Alabama","countyFIPS":"033","name":"Colbert","statePostal":"AL"},"arcs":[[27,28,29,30]]},{"type":"Polygon","id":"01027","properties":{"stateFIPS":"01","state":"Alabama","countyFIPS":"027","name":"Clay","statePostal":"AL"},"arcs":[[31,-11,-1,-25,32]]},{"type":"Polygon","id":"01127","properties":{"stateFIPS":"01","state":"Alabama","countyFIPS":"127","name":"Walker","statePostal":"AL"},"arcs":[[33,34,35,36,37,38,39]]},{"type":"Polygon","id":"01007","properties":{"stateFIPS":"01","state":"Alabama","countyFIPS":"007","name":"Bibb","statePostal":"AL"},"arcs":[[40,41,42,43,44,45]]},{"type":"Polygon","id":"01107","properties":{"stateFIPS":"01","state":"Alabama","countyFIPS":"107","name":"Pickens","statePostal":"AL"},"arcs":[[46,47,48,49,50,51]]},{"type":"Polygon","id":"01053","properties":{"stateFIPS":"01","state":"Alabama","countyFIPS":"053","name":"Escambia","statePostal":"AL"},"arcs":[[52,53,54,55,56]]},{"type":"Polygon","id":"01047","properties":{"stateFIPS":"01","state":"Alabama","countyFIPS":"047","name":"Dallas","statePostal":"AL"},"arcs":[[57,58,-22,59,-13,60]]},{"type":"Polygon","id":"01013","properties":{"stateFIPS":"01","state":"Alabama","countyFIPS":"013","name":"Butler","statePostal":"AL"},"arcs":[[61,62,63,64,65,-15]]},{"type":"Polygon","id":"01031","properties":{"stateFIPS":"01","state":"Alabama","countyFIPS":"031","name":"Coffee","statePostal":"AL"},"arcs":[[66,67,68,69,70]]},{"type":"Polygon","id":"01121","properties":{"stateFIPS":"01","state":"Alabama","countyFIPS":"121","name":"Talladega","statePostal":"AL"},"arcs":[[71,72,73,-33,-24,74]]},{"type":"Polygon","id":"01073","properties":{"stateFIPS":"01","state":"Alabama","countyFIPS":"073","name":"Jefferson","statePostal":"AL"},"arcs":[[-37,75,76,77,-42,78]]},{"type":"Polygon","id":"01115","properties":{"stateFIPS":"01","state":"Alabama","countyFIPS":"115","name":"St. Clair","statePostal":"AL"},"arcs":[[79,80,-72,81,-77,82]]},{"type":"Polygon","id":"01069","properties":{"stateFIPS":"01","state":"Alabama","countyFIPS":"069","name":"Houston","statePostal":"AL"},"arcs":[[83,84,85,86]]},{"type":"Polygon","id":"01059","properties":{"stateFIPS":"01","state":"Alabama","countyFIPS":"059","name":"Franklin","statePostal":"AL"},"arcs":[[-30,87,88,89,90]]},{"type":"Polygon","id":"01005","properties":{"stateFIPS":"01","state":"Alabama","countyFIPS":"005","name":"Barbour","statePostal":"AL"},"arcs":[[91,92,93,94,95,96]]},{"type":"Polygon","id":"01113","properties":{"stateFIPS":"01","state":"Alabama","countyFIPS":"113","name":"Russell","statePostal":"AL"},"arcs":[[97,98,-93,99,100]]},{"type":"Polygon","id":"01009","properties":{"stateFIPS":"01","state":"Alabama","countyFIPS":"009","name":"Blount","statePostal":"AL"},"arcs":[[101,102,103,-83,-76,-36]]},{"type":"Polygon","id":"01045","properties":{"stateFIPS":"01","state":"Alabama","countyFIPS":"045","name":"Dale","statePostal":"AL"},"arcs":[[104,-96,105,-87,106,-69]]},{"type":"Polygon","id":"01019","properties":{"stateFIPS":"01","state":"Alabama","countyFIPS":"019","name":"Cherokee","statePostal":"AL"},"arcs":[[107,108,109,110,111]]},{"type":"Polygon","id":"01049","properties":{"stateFIPS":"01","state":"Alabama","countyFIPS":"049","name":"DeKalb","statePostal":"AL"},"arcs":[[112,113,-112,114,115]]},{"type":"Polygon","id":"01023","properties":{"stateFIPS":"01","state":"Alabama","countyFIPS":"023","name":"Choctaw","statePostal":"AL"},"arcs":[[116,117,118,119,120]]},{"type":"Polygon","id":"01015","properties":{"stateFIPS":"01","state":"Alabama","countyFIPS":"015","name":"Calhoun","statePostal":"AL"},"arcs":[[-81,121,-110,122,-73]]},{"type":"Polygon","id":"01021","properties":{"stateFIPS":"01","state":"Alabama","countyFIPS":"021","name":"Chilton","statePostal":"AL"},"arcs":[[-44,123,-27,124,-18,-59,125]]},{"type":"Polygon","id":"01089","properties":{"stateFIPS":"01","state":"Alabama","countyFIPS":"089","name":"Madison","statePostal":"AL"},"arcs":[[126,127,128,129,130]]},{"type":"Polygon","id":"01101","properties":{"stateFIPS":"01","state":"Alabama","countyFIPS":"101","name":"Montgomery","statePostal":"AL"},"arcs":[[-20,131,132,133,134,135,136]]},{"type":"Polygon","id":"01055","properties":{"stateFIPS":"01","state":"Alabama","countyFIPS":"055","name":"Etowah","statePostal":"AL"},"arcs":[[137,-115,-111,-122,-80,-104]]},{"type":"Polygon","id":"01133","properties":{"stateFIPS":"01","state":"Alabama","countyFIPS":"133","name":"Winston","statePostal":"AL"},"arcs":[[-89,138,139,-34,140]]},{"type":"Polygon","id":"01099","properties":{"stateFIPS":"01","state":"Alabama","countyFIPS":"099","name":"Monroe","statePostal":"AL"},"arcs":[[-16,-66,141,-53,142,143]]},{"type":"Polygon","id":"01079","properties":{"stateFIPS":"01","state":"Alabama","countyFIPS":"079","name":"Lawrence","statePostal":"AL"},"arcs":[[-29,144,145,146,147,-139,-88]]},{"type":"Polygon","id":"01041","properties":{"stateFIPS":"01","state":"Alabama","countyFIPS":"041","name":"Crenshaw","statePostal":"AL"},"arcs":[[148,-136,149,-67,150,-63]]},{"type":"Polygon","id":"01043","properties":{"stateFIPS":"01","state":"Alabama","countyFIPS":"043","name":"Cullman","statePostal":"AL"},"arcs":[[-148,151,152,-102,-35,-140]]},{"type":"Polygon","id":"01087","properties":{"stateFIPS":"01","state":"Alabama","countyFIPS":"087","name":"Macon","statePostal":"AL"},"arcs":[[153,-5,154,-101,155,-133]]},{"type":"Polygon","id":"01081","properties":{"stateFIPS":"01","state":"Alabama","countyFIPS":"081","name":"Lee","statePostal":"AL"},"arcs":[[156,157,-98,-155,-4]]},{"type":"Polygon","id":"01071","properties":{"stateFIPS":"01","state":"Alabama","countyFIPS":"071","name":"Jackson","statePostal":"AL"},"arcs":[[158,-113,159,-128]]},{"type":"Polygon","id":"01129","properties":{"stateFIPS":"01","state":"Alabama","countyFIPS":"129","name":"Washington","statePostal":"AL"},"arcs":[[-120,160,161,162,163]]},{"type":"Polygon","id":"01109","properties":{"stateFIPS":"01","state":"Alabama","countyFIPS":"109","name":"Pike","statePostal":"AL"},"arcs":[[-135,164,-97,-105,-68,-150]]},{"type":"Polygon","id":"01051","properties":{"stateFIPS":"01","state":"Alabama","countyFIPS":"051","name":"Elmore","statePostal":"AL"},"arcs":[[-26,-6,-154,-132,-19,-125]]},{"type":"Polygon","id":"01035","properties":{"stateFIPS":"01","state":"Alabama","countyFIPS":"035","name":"Conecuh","statePostal":"AL"},"arcs":[[-65,165,-54,-142]]},{"type":"Polygon","id":"01011","properties":{"stateFIPS":"01","state":"Alabama","countyFIPS":"011","name":"Bullock","statePostal":"AL"},"arcs":[[-156,-100,-92,-165,-134]]},{"type":"Polygon","id":"01105","properties":{"stateFIPS":"01","state":"Alabama","countyFIPS":"105","name":"Perry","statePostal":"AL"},"arcs":[[-45,-126,-58,166,167]]},{"type":"Polygon","id":"01093","properties":{"stateFIPS":"01","state":"Alabama","countyFIPS":"093","name":"Marion","statePostal":"AL"},"arcs":[[-90,-141,-40,168,169,170]]},{"type":"Polygon","id":"01039","properties":{"stateFIPS":"01","state":"Alabama","countyFIPS":"039","name":"Covington","statePostal":"AL"},"arcs":[[-64,-151,-71,171,172,-55,-166]]},{"type":"Polygon","id":"01057","properties":{"stateFIPS":"01","state":"Alabama","countyFIPS":"057","name":"Fayette","statePostal":"AL"},"arcs":[[-169,-39,173,-48,174]]},{"type":"Polygon","id":"01061","properties":{"stateFIPS":"01","state":"Alabama","countyFIPS":"061","name":"Geneva","statePostal":"AL"},"arcs":[[-70,-107,-86,175,-172]]},{"type":"Polygon","id":"01125","properties":{"stateFIPS":"01","state":"Alabama","countyFIPS":"125","name":"Tuscaloosa","statePostal":"AL"},"arcs":[[-174,-38,-79,-41,176,177,-49]]},{"type":"Polygon","id":"01063","properties":{"stateFIPS":"01","state":"Alabama","countyFIPS":"063","name":"Greene","statePostal":"AL"},"arcs":[[-50,-178,178,179,180]]},{"type":"Polygon","id":"01103","properties":{"stateFIPS":"01","state":"Alabama","countyFIPS":"103","name":"Morgan","statePostal":"AL"},"arcs":[[181,-130,182,-152,-147]]},{"type":"Polygon","id":"01075","properties":{"stateFIPS":"01","state":"Alabama","countyFIPS":"075","name":"Lamar","statePostal":"AL"},"arcs":[[-170,-175,-47,183]]},{"type":"Polygon","id":"01083","properties":{"stateFIPS":"01","state":"Alabama","countyFIPS":"083","name":"Limestone","statePostal":"AL"},"arcs":[[184,-131,-182,-146,185]]},{"type":"Polygon","id":"01085","properties":{"stateFIPS":"01","state":"Alabama","countyFIPS":"085","name":"Lowndes","statePostal":"AL"},"arcs":[[-21,-137,-149,-62,-14,-60]]},{"type":"Polygon","id":"01095","properties":{"stateFIPS":"01","state":"Alabama","countyFIPS":"095","name":"Marshall","statePostal":"AL"},"arcs":[[-129,-160,-116,-138,-103,-153,-183]]},{"type":"Polygon","id":"01017","properties":{"stateFIPS":"01","state":"Alabama","countyFIPS":"017","name":"Chambers","statePostal":"AL"},"arcs":[[-10,186,-157,-3]]},{"type":"Polygon","id":"01029","properties":{"stateFIPS":"01","state":"Alabama","countyFIPS":"029","name":"Cleburne","statePostal":"AL"},"arcs":[[-74,-123,-109,187,-8,-32]]},{"type":"Polygon","id":"01077","properties":{"stateFIPS":"01","state":"Alabama","countyFIPS":"077","name":"Lauderdale","statePostal":"AL"},"arcs":[[-186,-145,-28,188]]},{"type":"Polygon","id":"01025","properties":{"stateFIPS":"01","state":"Alabama","countyFIPS":"025","name":"Clarke","statePostal":"AL"},"arcs":[[189,-17,-144,190,-161,-119]]},{"type":"Polygon","id":"01065","properties":{"stateFIPS":"01","state":"Alabama","countyFIPS":"065","name":"Hale","statePostal":"AL"},"arcs":[[-177,-46,-168,191,-179]]},{"type":"Polygon","id":"01097","properties":{"stateFIPS":"01","state":"Alabama","countyFIPS":"097","name":"Mobile","statePostal":"AL"},"arcs":[[-163,192,193]]},{"type":"Polygon","id":"01003","properties":{"stateFIPS":"01","state":"Alabama","countyFIPS":"003","name":"Baldwin","statePostal":"AL"},"arcs":[[-162,-191,-143,-57,194,-193]]},{"type":"Polygon","id":"01091","properties":{"stateFIPS":"01","state":"Alabama","countyFIPS":"091","name":"Marengo","statePostal":"AL"},"arcs":[[195,-180,-192,-167,-61,-12,-190,-118]]},{"type":"Polygon","id":"01067","properties":{"stateFIPS":"01","state":"Alabama","countyFIPS":"067","name":"Henry","statePostal":"AL"},"arcs":[[-95,196,-84,-106]]},{"type":"Polygon","id":"01119","properties":{"stateFIPS":"01","state":"Alabama","countyFIPS":"119","name":"Sumter","statePostal":"AL"},"arcs":[[-51,-181,-196,-117,197]]},{"type":"Polygon","id":"01117","properties":{"stateFIPS":"01","state":"Alabama","countyFIPS":"117","name":"Shelby","statePostal":"AL"},"arcs":[[-78,-82,-75,-23,-124,-43]]}]}},"arcs":[[[687606,598761],[9634,3152],[89714,280]],[[786954,602193],[16959,145]],[[803913,602338],[0,-79257]],[[803913,523081],[-24285,-3343],[-4717,-3164],[301,-21231]],[[775212,495343],[-28700,-3108],[401,-18168],[-24887,-246]],[[722026,473821],[1706,54705],[-35524,89]],[[688208,528615],[-1806,13439],[1204,56707]],[[789864,683630],[82689,1152],[11942,-3902]],[[884495,680880],[2910,-11460],[16157,-62442],[1204,-4483]],[[904766,602495],[-100853,-157]],[[786954,602193],[3512,44744],[-602,36693]],[[223883,368860],[12645,2952],[-402,26542],[28600,100],[2108,27862],[11741,-224]],[[278575,426092],[41244,-13774],[41044,-31718],[75765,100]],[[436628,380700],[14049,78],[-301,-18033]],[[450376,362745],[-14350,-101],[602,-27414]],[[436628,335230],[-166081,-291]],[[270547,334939],[-33317,-447],[-13046,10174],[-301,24194]],[[433617,509620],[57100,-514],[-201,9201],[84195,358]],[[574711,518665],[502,-62241]],[[575213,456424],[-13548,-939],[-10336,-12757]],[[551329,442728],[-43853,11047],[-35725,-995],[-9734,-17263],[301,6451]],[[462318,441968],[-25590,40987],[-3111,26665]],[[545509,584182],[1806,14198],[5620,3042]],[[552935,601422],[88509,301]],[[641444,601723],[45660,45],[502,-3007]],[[688208,528615],[-92122,2751],[-10738,-3041]],[[585348,528325],[-22980,12622],[1605,10420],[-18063,13730],[-401,19085]],[[103663,975760],[34822,-2024],[14852,-16334],[31710,-15149],[78977,20996],[27295,-6775]],[[291319,956474],[-5318,-31182],[-23482,-17553]],[[262519,907739],[-170497,3064]],[[92022,910803],[1505,8564],[10136,56393]],[[731560,684223],[-10035,-6127],[29402,-22],[4817,6115],[34120,-559]],[[641444,601723],[402,19096],[14651,-246],[602,21299],[38535,-447],[1104,18346],[14752,3008],[5218,21433],[14852,11]],[[232714,789564],[117311,-1745],[13045,2371],[5319,-2505]],[[368389,787685],[16558,-21578],[35926,-6674]],[[420873,759433],[2709,-8978]],[[423582,750455],[-14651,-5870],[-14451,-27380],[-34019,-8911],[-1806,-12108],[-23884,-5445],[1205,-3544]],[[335976,687197],[-14351,257],[-100,15317],[-14651,-67],[-14752,3141]],[[292122,705845],[0,18213],[-29202,615],[-903,36727],[-29202,917],[0,9045]],[[232815,771362],[-101,18202]],[[292624,580593],[28901,581],[10236,26542],[23081,-503],[100,13785],[37230,10543]],[[392172,631541],[10938,-100]],[[403110,631441],[302,-16871],[40441,-24250]],[[443853,590320],[1405,-44699],[-40040,167]],[[405218,545788],[-83894,-1151],[0,9123],[-28499,-134]],[[292825,553626],[-201,26967]],[[54290,691602],[91721,-2080]],[[146011,689522],[29603,168]],[[175614,689690],[803,-77670]],[[176417,612020],[-36528,-15775],[-50576,-8564],[-6323,-8665]],[[82990,579016],[-47064,-961]],[[35926,578055],[6422,40349],[3613,21802],[8329,51396]],[[238434,212593],[15856,-3577],[36829,6909]],[[291119,215925],[185449,190],[-2409,-12354],[20271,-2102]],[[494430,201659],[0,-38348],[3312,-2661]],[[497742,160650],[-27196,167],[-12945,79],[-26794,67],[-65629,279],[-201,0],[-41646,-123],[-31811,-78],[-26192,-101],[-22177,-33]],[[243151,160907],[-4616,581],[-101,51105]],[[278374,435025],[14350,101],[-401,36582],[87305,1464],[25991,50122]],[[405619,523294],[0,-13864],[27998,190]],[[462318,441968],[-9935,-2482],[-3914,-11303],[15153,-10498],[-27396,55],[402,-37040]],[[278575,426092],[-201,8933]],[[450376,362745],[114501,514]],[[564877,363259],[-101,-64645],[-14250,-78],[101,-27179]],[[550627,271357],[-56598,-291]],[[494029,271066],[-38535,257],[-18866,22495],[301,25178]],[[436929,318996],[-301,16234]],[[635925,253513],[-201,18805],[14250,1622],[-602,16748]],[[649372,290688],[99749,44]],[[749121,290732],[-602,-88201]],[[748519,202531],[-93427,-2996],[-18966,2124]],[[636126,201659],[-803,45638],[602,6216]],[[584345,661683],[26994,24876],[13046,-3219],[18364,26094],[-6222,16536],[12946,-4014]],[[649473,721956],[26492,-939],[15655,-18436],[55996,-190],[-401,-6138]],[[747215,696253],[-502,-3142],[-15153,-8888]],[[552935,601422],[-3412,15943],[12644,13025],[28098,11616],[4516,12064],[-10436,7613]],[[423582,750455],[19468,5847],[34822,-559],[31912,-14132],[18866,-1610]],[[528650,740001],[9734,-33],[5017,-9190],[2308,-36683]],[[545709,694095],[-100,-4562],[-43954,-12052],[-43652,-28141],[-14551,146],[-26794,-15999],[-13548,-2046]],[[392172,631541],[0,6071],[-31811,10890],[-4215,3153],[-41043,26665],[20873,8877]],[[599096,776572],[9935,9123],[25489,1085],[15755,-18727],[21676,-11974]],[[671951,756079],[5921,-16447],[-28399,-17676]],[[584345,661683],[100,23311],[-29002,23],[-9734,9078]],[[528650,740001],[100,7670],[47968,7088],[16156,9436],[6222,12377]],[[853085,227340],[66533,-1520],[25288,201]],[[944906,226021],[-301,-2851],[-5118,-7625],[201,-15094],[20070,-16367],[4115,-6843],[2709,-4595],[2409,-11057],[-8029,-11],[-32012,11],[-52383,-235],[-43352,-335]],[[833215,161019],[703,42250],[-62920,-984]],[[770998,202285],[12544,15093],[50376,-4438],[19167,14400]],[[262519,907739],[0,-54917]],[[262519,852822],[-29403,503]],[[233116,853325],[-150527,2940]],[[82589,856265],[5118,29706],[4315,24832]],[[785850,345616],[19669,24496],[44455,3679],[5118,27559]],[[855092,401350],[42549,269],[20371,-18045],[37331,111]],[[955343,383685],[-3412,-14724],[-1204,-5121],[-12845,-15484],[-7828,-11326],[3613,-12332],[1003,-3622]],[[934670,321076],[-25388,-12668],[-55896,884],[-100,-18247]],[[853286,291045],[-92725,-290]],[[760561,290755],[3512,1341],[19368,31048],[2409,22472]],[[848368,456413],[29102,201],[-1104,12097],[76769,895],[16257,7793]],[[969392,477399],[401,-649],[7828,-13439],[-2609,-13349],[-603,-3309],[-6924,-5546],[14651,-6440],[17863,-8899],[-7928,-6809],[-2810,-2471],[-18866,-7021],[-17059,-10342],[3211,-10174],[-1204,-5266]],[[855092,401350],[-4817,-22],[-1706,18425]],[[848569,419753],[-201,36660]],[[420873,759433],[10838,10677],[36527,8955],[30306,22406],[-2007,6954],[25590,5579],[-903,1274],[4716,2762],[3814,5668],[2809,1062],[12544,17117],[18365,1465]],[[563472,843352],[41846,-33530]],[[605318,809822],[-8028,-12253],[-10637,-21075],[12443,78]],[[749121,290732],[11440,23]],[[853286,291045],[-201,-63705]],[[770998,202285],[-22479,246]],[[826291,898717],[3011,-10342],[7626,-27369],[3312,-12030],[9433,-33709],[2308,-9257],[6222,-24418]],[[858203,781592],[-26894,-1509],[-9734,-3243]],[[821575,776840],[-3412,3209],[-54993,2449]],[[763170,782498],[-16457,28699],[-12243,1141],[-602,18604]],[[733868,830942],[0,9324],[19468,3041],[40943,28622],[19067,22249],[12945,4539]],[[674059,888688],[11741,1174],[64325,29907],[56698,49350]],[[806823,969119],[5921,-23087],[7626,-26430],[2108,-7346],[3813,-13539]],[[733868,830942],[-73357,156]],[[660511,831098],[-3613,42485],[17161,15105]],[[13246,435249],[137180,391]],[[150426,435640],[-24786,-5299],[3412,-20907],[-29805,-37466],[11240,-3354]],[[110487,368614],[-13447,-8363],[-16458,-28386],[25790,-24116]],[[106372,307749],[-104967,-280]],[[1405,307469],[-1405,19409],[0,21578],[0,8229],[4315,25077],[6222,36526],[803,4707],[1906,12254]],[[671951,756079],[10738,2001],[8831,2750],[7225,10398],[34420,8933],[29403,-4595],[602,6932]],[[821575,776840],[-703,-10934],[-29503,-24228],[-201,-26139],[-43953,-19286]],[[443853,590320],[-201,4595],[75966,-392],[25891,-10341]],[[585348,528325],[-10737,-626],[100,-9034]],[[405619,523294],[-401,22494]],[[471048,996623],[88309,-258],[41746,79],[2007,11]],[[603110,996455],[15254,-11158],[-19167,-101],[-9433,-63750],[9031,-6943]],[[598795,914503],[-903,-18145],[-26192,-6921],[-30707,4852],[-4616,9034]],[[536377,903323],[-8028,7401],[-18866,-6786],[-12042,7848],[-28099,-7457]],[[469342,904329],[1706,92294]],[[575213,456424],[41746,19197],[19468,-13707],[40742,-6272],[6523,2884]],[[683692,458526],[8931,-17542],[20071,-12913]],[[712694,428071],[-18766,-425],[-3512,-4561],[401,-22797],[201,-18939]],[[691018,381349],[401,-17475],[-54791,-224]],[[636628,363650],[-30909,-290],[-401,18112],[-28700,-190]],[[576618,381282],[-603,33104],[-100,7391],[-3813,1967],[-7426,2069],[-2710,2191],[-6121,-548],[-1204,2728],[2910,9850],[-6222,2694]],[[605318,809822],[27195,15395],[27195,2863],[803,3018]],[[262519,852822],[117310,-1107]],[[379829,851715],[-502,-64209],[-10938,179]],[[232714,789564],[402,63761]],[[436929,318996],[-40642,-7256],[-23483,-15887],[-8730,-25704],[-72955,-54224]],[[238434,212593],[-28499,12276],[-13247,-1207]],[[196688,223662],[-5519,5713],[33316,20605],[25690,2493],[-12845,17565],[15153,7222],[-401,30030],[14250,157],[4215,27492]],[[291319,956474],[23081,-738],[12945,-9559],[10337,1632]],[[337682,947809],[10637,973],[32915,-16155]],[[381234,932627],[-1405,-77882]],[[379829,854745],[0,-3030]],[[564877,363259],[12042,-179],[-301,18202]],[[636628,363650],[-2208,-36828],[14250,101],[401,-26732],[-9132,-9783],[9433,280]],[[635925,253513],[-23181,3254],[-903,15250],[-33116,-16145],[-401,15865],[-27697,-380]],[[379829,854745],[147617,-1901]],[[527446,852844],[29202,-403],[6824,-9089]],[[683692,458526],[47667,11672],[-9333,3623]],[[775212,495343],[57702,-20706],[14250,22],[1204,-18246]],[[848569,419753],[-118213,-559],[-11842,15339],[0,-6339],[-5820,-123]],[[803913,523081],[5118,1644],[80983,-1174],[44957,4371]],[[934971,527922],[2810,-4438],[7226,-15161],[3512,-10442],[1706,-5210],[17561,-12410],[1606,-2862]],[[603110,996455],[125138,-850],[72353,-492],[2710,-12667],[3512,-13327]],[[674059,888688],[-7226,-2393],[-4014,10040],[-14149,18101],[-5319,34],[-1505,11],[-301,11],[-402,0],[-903,11],[-100,0],[-1104,11],[-4717,34],[-5117,45],[-201,0],[-703,0],[-802,11],[-2710,22],[-301,0],[-602,11],[-2408,12],[-1205,0],[-702,0],[-402,11],[-1103,-11],[-2308,-12],[-803,0],[-1907,0],[-602,-11],[-401,0],[-1405,0],[-4516,-22],[-1405,-11],[-1706,0],[-1204,-11],[-301,0],[-301,0],[-2409,-12],[0,-33],[0,-34]],[[106372,307749],[2609,-6205],[-2910,-2281],[4717,-13439],[5820,-2303],[6724,157],[-1004,-4964],[16959,-6273],[7828,-793],[5017,-4964],[5118,-2348],[-8028,-10331],[13347,-10498],[-5821,-14479],[-14450,-1420],[3713,-25793]],[[146011,201815],[-7426,-6328]],[[138585,195487],[-13849,-3857],[-85900,-89],[-28600,-6183]],[[10236,185358],[-4616,64231],[-201,3041],[-2810,38874],[-1204,15965]],[[691018,381349],[14149,2258],[14752,-3041],[2609,-16748],[26292,0],[-201,-18190],[37231,-12]],[[494029,271066],[11038,-25346],[-10938,-16412],[301,-27649]],[[278374,435025],[-14350,-67],[-101,36560]],[[263923,471518],[-200,36336],[14350,33],[502,36560],[14250,9179]],[[232815,771362],[-28902,-101],[-59407,1085]],[[144506,772346],[0,21399],[-9835,6250],[-61615,1308]],[[73056,801303],[1103,5892],[8430,49070]],[[636126,201659],[803,-37365],[903,-4092]],[[637832,160202],[-49674,79],[-6623,22],[-48871,145],[-34922,202]],[[292122,705845],[-58103,1622],[-9835,-18448],[-48570,671]],[[146011,689522],[-1505,82824]],[[833215,161019],[-2709,-23],[-22780,-167],[-47566,-369],[-40241,-381],[-39538,56],[-42549,67]],[[292624,580593],[-82087,715]],[[210537,581308],[-32614,2180],[200,16033],[-1806,8989],[100,3510]],[[210537,581308],[-4014,-12041],[-20773,-10823],[-7727,-11929],[5218,-6350],[-15956,-9984],[17361,-2113],[-1405,-24787],[21375,-9246],[-14250,-1543],[-6924,-12086]],[[183442,480406],[-3512,4237],[-7928,-2661]],[[172002,481982],[-12544,12601],[16056,2661],[-24586,5702],[-34922,-8207],[-15655,37231],[8530,413],[-35825,31763],[8931,1532],[1003,13338]],[[381234,932627],[55293,-22227],[32815,-6071]],[[536377,903323],[-703,-1263],[-8028,-35319],[-200,-13897]],[[54290,691602],[5620,34480],[1706,9648],[11440,65573]],[[351630,998110],[104767,-1297],[14651,-190]],[[337682,947809],[-4918,3131],[17762,8877],[1104,38293]],[[904766,602495],[12945,-49786],[502,-1845],[6523,-7245],[10235,-15697]],[[858203,781592],[3412,-13059],[7325,-27984],[6222,-24026],[6824,-25793],[2509,-9850]],[[103663,975760],[-15856,6317],[-12744,15328],[-803,2594],[56799,-447],[4214,0],[37130,-56],[63422,-403],[5319,-44],[106773,-895],[2108,-22],[1605,-22]],[[110487,368614],[113396,246]],[[196688,223662],[-10838,4528],[-8931,-18403],[-30908,-7972]],[[263923,471518],[-57099,-235],[100,9123],[-23482,0]],[[138585,195487],[9232,-3231],[-10135,-12074],[9834,-8654],[-6723,-16815],[11440,-6775],[-15956,-10152],[10236,-12522],[-22880,-15418],[5017,-14310]],[[128650,95536],[-14952,-8386],[-803,-11840],[-4716,-8776],[-6122,-9503],[-602,-20729],[-8530,-16971],[-16558,112],[-17361,-481],[-15052,10453],[-14651,3992],[-8731,-3891],[-2509,36392],[-2308,39422],[0,805],[-3813,54951],[-1706,24272]],[[243151,160907],[1906,-9615],[-11941,-17911],[25890,-20583],[5219,-6104],[22679,-9548],[11841,-7413],[-301,-11057],[-8429,-11326],[-3713,-8944],[8329,-10498],[13447,-4327],[-18164,-6999],[-5720,-12365],[-18464,-13316],[-38736,-6429],[-45358,-4472],[-20773,2281],[24285,8486],[2709,9290],[-19066,12399],[-13749,13115],[-5418,8620],[8931,13293],[-3713,7323],[-4516,13976],[-21676,6753]],[[150426,435640],[-32313,13920],[4115,11817],[49774,20605]],[[934670,321076],[1807,-6340],[-1807,-7893],[18766,-15630],[100,-10342],[4516,-5467],[-2810,-5255],[-5519,-10710],[1606,-7748],[-7426,-14322],[1204,-8631],[-201,-2717]],[[13246,435249],[8932,56371],[4515,27973],[7226,45437],[2007,13025]]],"transform":{"scale":[0.000003576925837303096,0.00000477973543232209],"translate":[-88.46868533589434,30.228323420618416]}}